complexion/__init__.py
complexion/basemath/__init__.py
complexion/basemath/base.py
complexion-0.0.1.dist-info/METADATA
complexion-0.0.1.dist-info/WHEEL
complexion-0.0.1.dist-info/licenses/LICENSE
complexion-0.0.1.dist-info/RECORD
