Metadata-Version: 2.4
Name: complexion
Version: 0.0.1
Summary: Usable in math projects
Author-email: mark4d4 <sevcow4674@gmail.com>
License-Expression: MIT
License-File: LICENSE
Classifier: Operating System :: OS Independent
Classifier: Programming Language :: Python :: 3
Requires-Python: >=3.10
